ripledd/__init__.py
ripledd/__main__.py
ripledd/constants.py
ripledd/main.py
ripledd/setup.py
ripledd_python-1.0.dist-info/LICENSE
ripledd_python-1.0.dist-info/METADATA
ripledd_python-1.0.dist-info/WHEEL
ripledd_python-1.0.dist-info/top_level.txt
ripledd_python-1.0.dist-info/RECORD
