Metadata-Version: 2.1
Name: ripledd-python
Version: 1.0
Summary: A nice and sweet API wrapper made for Ripledd
Author-email: Aditya Priyadarshi <adityapriyadarshi669@gmail.com>
Project-URL: Homepage, https://github.com/foxy4096/ripledd-python
Project-URL: Bug Tracker, https://github.com/foxy4096/ripledd-python/ssues
Classifier: Development Status :: 3 - Alpha
Classifier: Intended Audience :: Education
Classifier: Programming Language :: Python :: 2
Classifier: Programming Language :: Python :: 3
Classifier: Operating System :: MacOS :: MacOS X
Classifier: Operating System :: Microsoft :: Windows
Requires-Python: >=3.7
License-File: LICENSE
